st_paywall/__init__.py
st_paywall/aggregate_auth.py
st_paywall/buymeacoffee_auth.py
st_paywall/stripe_auth.py
st_paywall-1.0.1.dist-info/LICENSE
st_paywall-1.0.1.dist-info/METADATA
st_paywall-1.0.1.dist-info/WHEEL
st_paywall-1.0.1.dist-info/top_level.txt
st_paywall-1.0.1.dist-info/RECORD
