Metadata-Version: 2.2
Name: st-paywall
Version: 1.0.1
Summary: A Python package for creating subscription Streamlit apps
Author-email: Tyler Richards <tylerjrichards@gmail.com>
License: MIT
Requires-Python: >=3.8.0
License-File: LICENSE
Requires-Dist: stripe
Requires-Dist: streamlit>=1.42.0
